{
  "os": "Amazon Linux",
  "version": "2",
  "codename": "Karoo",
  "kernel": "5.10.205-195.804.amzn2.x86_64",
  "arch": "x86_64",
  "hostname": "ip-10-0-0-40",
  "ssh_banner": "SSH-2.0-OpenSSH_7.4",
  "motd": "       __|  __|_  )\n       _|  (     /   Amazon Linux 2 AMI\n      ___|\\___|\\___|",
  "packages": {
    "openssh-server": "7.4p1-22.amzn2.0.4",
    "httpd": "2.4.58-1.amzn2",
    "docker": "20.10.25-1.amzn2.0.3",
    "python3": "3.7.16-1.amzn2.0.6",
    "aws-cli": "1.32.23-1.amzn2.0.1"
  },
  "services": ["sshd", "httpd", "docker", "crond", "amazon-ssm-agent"],
  "users": [
    {"name": "root", "uid": 0, "shell": "/bin/bash"},
    {"name": "ec2-user", "uid": 1000, "shell": "/bin/bash"},
    {"name": "apache", "uid": 48, "shell": "/sbin/nologin"}
  ],
  "network": {
    "interface": "eth0",
    "ip": "10.0.0.40",
    "netmask": "255.255.255.0",
    "gateway": "10.0.0.1",
    "dns": ["10.0.0.2"]
  },
  "tcp_fingerprint": {
    "ttl": 64,
    "window_size": 26883,
    "options": "mss 8961,sackOK,TS val ecr,nop,wscale 8"
  }
}
